src/__init__.py
src/configuration.py
src/crypto.py
src/decorator.py
src/exceptions.py
src/mongodb.py
src/pd.py
src/settings.py
src/tasks.py
src/test_learn.py
src/time.py
src/airflow/__init__.py
src/airflow/operators.py
src/api/__init__.py
src/api/endpoints.py
src/aws/__init__.py
src/aws/__main__.py
src/aws/connector.py
src/aws/analysis/__init__.py
src/aws/analysis/athena.py
src/aws/collection/__init__.py
src/aws/collection/kinesis_stream.py
src/aws/storage/__init__.py
src/aws/storage/dynamo_crud.py
src/aws/storage/s3_connect.py
src/basics/__init__.py
src/basics/compression.py
src/basics/data_struct.py
src/basics/decorator.py
src/basics/enum.py
src/basics/inheritance.py
src/basics/inspect_module.py
src/basics/static_class_method.py
src/basics/with_stat.py
src/cnx/__init__.py
src/cnx/postgre_cnx.py
src/design_patterns/__init__.py
src/design_patterns/creation/__init__.py
src/design_patterns/creation/abstract_factory.py
src/models/__init__.py
src/models/database.py
src/spark/__init__.py
src/spark/main.py
src/sql/__init__.py
src/sql/base.py
src/sql/crud.py
src/sql/db.py
src/sql/model.py
src/sql/session.py
src/sql/settings.py
src/utils/__init__.py
src/utils/dates.py
src/utils/email_sender.py
src/utils/file_utils.py
learn_python-0.0.1.dist-info/METADATA
learn_python-0.0.1.dist-info/WHEEL
learn_python-0.0.1.dist-info/top_level.txt
learn_python-0.0.1.dist-info/RECORD
