Metadata-Version: 2.1
Name: learn-python
Version: 0.0.1
Summary: This is learn python module
Home-page: https://github.com/Massipssa/learn-python/
Author: Massipssa Kerrache
Author-email: kerrache.massipssa@gmail.com
License: Test License, Version 0.1
Download-URL: https://pypi.org/project/learn-python/0.0.1
Platform: UNKNOWN
Requires-Dist: Flask-SQLAlchemy (==2.4.1)
Requires-Dist: SQLAlchemy (==1.3.15)
Requires-Dist: SQLAlchemy-JSONField (==0.9.0)
Requires-Dist: SQLAlchemy-Utils (==0.36.3)
Requires-Dist: coverage (==5.1)
Requires-Dist: boto3 (==1.14.28)
Requires-Dist: celery (==4.4.2)
Requires-Dist: pypandoc
Requires-Dist: pyspark (==2.3.1)
Requires-Dist: psycopg2
Requires-Dist: flake8
